{
  "word": "Food",
  "vietnamese": "Đồ ăn",
  "ipa": "/fuːd/",
  "explanations": [
    { "vi": "Đồ ăn là những thứ mà con người và động vật tiêu thụ để cung cấp dinh dưỡng, năng lượng và duy trì sự sống.", "en": "Food is what humans and animals consume to provide nutrition, energy, and sustain life through eating and drinking." }
  ],
  "examples": [
    { "en": "I like Vietnamese food", "vi": "Tôi thích đồ ăn Việt Nam" },
    { "en": "Healthy food is important", "vi": "Đồ ăn lành mạnh rất quan trọng" }
  ],
  "related": ["meal", "eat", "restaurant", "healthy", "cooking", "hungry", "delicious"],
  "audioUrl": null,
  "image": null
}

